yada/YADA-gene-diff.ipynb
yada/YADA.ipynb
yada/YADA.py
yada/__init__.py
yada/diffexp.py
yada_deconv-0.1.0.dist-info/LICENCE
yada_deconv-0.1.0.dist-info/METADATA
yada_deconv-0.1.0.dist-info/WHEEL
yada_deconv-0.1.0.dist-info/top_level.txt
yada_deconv-0.1.0.dist-info/RECORD
